wwpdb/utils/db/BirdSchemaDef.py
wwpdb/utils/db/ChemCompSchemaDef.py
wwpdb/utils/db/DBLoadUtil.py
wwpdb/utils/db/DaInternalSchemaDef.py
wwpdb/utils/db/DbLoadingApi.py
wwpdb/utils/db/FileActivityDb.py
wwpdb/utils/db/FileActivityDbCore.py
wwpdb/utils/db/FileActivityUtil.py
wwpdb/utils/db/FileMetadataParser.py
wwpdb/utils/db/MessageSchemaDef.py
wwpdb/utils/db/MyConnectionBase.py
wwpdb/utils/db/MyDbAdapter.py
wwpdb/utils/db/MyDbSqlGen.py
wwpdb/utils/db/MyDbUtil.py
wwpdb/utils/db/MyQueryDirectives.py
wwpdb/utils/db/MysqlSchemaImporter.py
wwpdb/utils/db/PdbDistroSchemaDef.py
wwpdb/utils/db/PdbxSchemaDef.py
wwpdb/utils/db/PdbxSchemaMapReader.py
wwpdb/utils/db/PrdChemCompSchemaDef.py
wwpdb/utils/db/SchemaDefBase.py
wwpdb/utils/db/SchemaDefLoader.py
wwpdb/utils/db/StatusHistory.py
wwpdb/utils/db/StatusHistoryExec.py
wwpdb/utils/db/StatusHistorySchemaDef.py
wwpdb/utils/db/StatusHistoryUtils.py
wwpdb/utils/db/StatusLoadWrapper.py
wwpdb/utils/db/WorkflowSchemaDef.py
wwpdb/utils/db/__init__.py
wwpdb_utils_db-0.35.0.dist-info/METADATA
wwpdb_utils_db-0.35.0.dist-info/WHEEL
wwpdb_utils_db-0.35.0.dist-info/entry_points.txt
wwpdb_utils_db-0.35.0.dist-info/RECORD
