Metadata-Version: 2.4
Name: wwpdb.utils.db
Version: 0.35.0
Summary: wwPDB Python DB Schema Utilities
Project-URL: Homepage, https://github.com/rcsb/py-wwpdb_utils_db
Author-email: Ezra Peisach <ezra.peisach@rcsb.org>
License-Expression: Apache-2.0
Classifier: Development Status :: 3 - Alpha
Classifier: Intended Audience :: Developers
Classifier: License :: OSI Approved :: Apache Software License
Classifier: Natural Language :: English
Classifier: Programming Language :: Python
Classifier: Programming Language :: Python :: 3
Classifier: Programming Language :: Python :: 3.6
Classifier: Programming Language :: Python :: 3.7
Classifier: Programming Language :: Python :: 3.8
Requires-Python: >=3.8
Requires-Dist: mmcif
Requires-Dist: mmcif-utils
Requires-Dist: mysqlclient
Requires-Dist: rcsb-utils-multiproc
Requires-Dist: scandir
Requires-Dist: sqlalchemy~=1.3
Requires-Dist: sqlparse
Requires-Dist: wwpdb-io
Requires-Dist: wwpdb-utils-config
Provides-Extra: dev
Requires-Dist: check-manifest; extra == 'dev'
Provides-Extra: status
Requires-Dist: wwpdb-utils-dp; extra == 'status'
Provides-Extra: test
Requires-Dist: coverage; extra == 'test'
